thrust/__init__.py
thrust/data/__init__.py
dap_thrust-0.0.5.dist-info/METADATA
dap_thrust-0.0.5.dist-info/WHEEL
dap_thrust-0.0.5.dist-info/top_level.txt
dap_thrust-0.0.5.dist-info/RECORD
