Metadata-Version: 2.1
Name: dap-thrust
Version: 0.0.5
Summary: PYDAP
Home-page: https://github.com/gitvipin/thrust
Author: Vipin Sharma
Author-email: sh.vipin@gmail.com
License: UNKNOWN
Platform: UNKNOWN
Classifier: Programming Language :: Python :: 3
Classifier: Operating System :: OS Independent
